setup.py
launchkey_pyramid.egg-info/PKG-INFO
launchkey_pyramid.egg-info/SOURCES.txt
launchkey_pyramid.egg-info/dependency_links.txt
launchkey_pyramid.egg-info/entry_points.txt
launchkey_pyramid.egg-info/not-zip-safe
launchkey_pyramid.egg-info/requires.txt
launchkey_pyramid.egg-info/top_level.txt
pyramid_launchkey/__init__.py