Metadata-Version: 1.1
Name: launchkey-pyramid
Version: 0.1
Summary: LaunchKey authentication extension for Pyramid
Home-page: https://github.com/LaunchKey/launchkey-pyramid
Author: Brad Porter
Author-email: UNKNOWN
License: MIT
Keywords: web pyramid pylons launchkey security authentication
Platform: UNKNOWN
Classifier: Programming Language :: Python
Classifier: Framework :: Pyramid
Classifier: Topic :: Internet :: WWW/HTTP
Classifier: Topic :: Internet :: WWW/HTTP :: WSGI :: Application
